Metadata-Version: 2.1
Name: whereismysock
Version: 2019.6.0
Summary: A convenient way to work with websocket data streams
Home-page: https://github.com/3kwa/whereismysock
Author: Eugene Van den Bulke
Author-email: eugene.vandenbulke@gmail.com
License: BSD
Platform: UNKNOWN
Classifier: License :: OSI Approved :: BSD License
Classifier: Programming Language :: Python :: 3.7
Classifier: Topic :: Software Development :: Libraries
